centaurs-0.1.0.dist-info/METADATA
centaurs-0.1.0.dist-info/WHEEL
centaurs-0.1.0.dist-info/license_files/LICENSE
centaurs/__init__.py
centaurs/centaurs.cpython-311-x86_64-linux-gnu.so
centaurs-0.1.0.dist-info/RECORD
